{
    "ID": "d3cbb3fd-aded-4a9d-81f5-787837d26f4c",
    "Last Name": "Yoneda",
    "First Name": "Bruce Taro",
    "URL": "https://www.cpsbc.ca/files/public-notifications/2020-11-19-Yoneda.pdf",
    "Date": "Nov 19, 2020",
    "Profile URL": "https://www.cpsbc.ca/public/registrant-directory/search-result/352983/Yoneda%2CBruce",
    "Summary": "Male",
    "Registration": "Practising",
    "Education": "MD\n - 1972  - University of Alberta",
    "Contact": "Shelbourne Medical Clinic 150-3200 Shelbourne St, Victoria, BC, V8P 5G8, Canada"
}